[
  {
    "vin": "VIN1_F_ALT",
    "dname": "VIN1_F_ALT",
    "failed": true,
    "risk_band": "red",
    "est_km": 135365.16,
    "median_rul": 0.0,
    "fw_p25": 577.5,
    "fw_p75": 652.5,
    "fleet_med": 601.0,
    "rul_last": 172.67903550078557,
    "clock_zone_last": "YELLOW",
    "gap": 11,
    "over_pred": 161.67903550078557,
    "m5_trans": [
      [
        "Jul 2024",
        "YELLOW",
        "VSI volatility"
      ],
      [
        "May 2025",
        "ORANGE",
        "VSI volatility"
      ],
      [
        "Oct 2025",
        "RED",
        "VSI volatility"
      ]
    ],
    "m5_final": "RED",
    "m5_peak": null,
    "breaches": [],
    "ged": true,
    "ged_lead": 21,
    "cdelta": 0.20000076293945312,
    "n_cross": 1,
    "cross": [
      [
        "GREEN\u2192YELLOW",
        true,
        "GED2 storm"
      ]
    ],
    "arch": "Early-warning (GED2 storm ~21d)",
    "snap": {
      "cols": [
        [
          "Early",
          "2024-05-31 00:00:00"
        ],
        [
          "Cond\u2192ORANGE",
          "2025-05-14 00:00:00"
        ],
        [
          "Cond\u2192RED",
          "2025-10-23 00:00:00"
        ],
        [
          "First deviation",
          "2025-11-08 00:00:00"
        ],
        [
          "Failure",
          "2025-11-29 00:00:00"
        ]
      ],
      "col_index": {
        "Early": 0,
        "Cond\u2192ORANGE": 1,
        "Cond\u2192RED": 2,
        "First deviation": 3,
        "Failure": 4
      },
      "rows": {
        "Effective zone": [
          [
            "GREEN",
            "#27AE60"
          ],
          [
            "YELLOW",
            "#F5A623"
          ],
          [
            "RED",
            "#C0392B"
          ],
          [
            "RED",
            "#C0392B"
          ],
          [
            "RED",
            "#C0392B"
          ]
        ],
        "RUL (schedule)": [
          [
            "663 d (GREEN)",
            "#27AE60"
          ],
          [
            "321 d (GREEN)",
            "#27AE60"
          ],
          [
            "190 d (GREEN)",
            "#27AE60"
          ],
          [
            "179 d (YELLOW)",
            "#F5A623"
          ],
          [
            "173 d (YELLOW)",
            "#F5A623"
          ]
        ],
        "Condition (M5)": [
          [
            "0.10 (GREEN)",
            "#27AE60"
          ],
          [
            "0.36 (ORANGE)",
            "#E67E22"
          ],
          [
            "0.62 (RED)",
            "#C0392B"
          ],
          [
            "0.70 (RED)",
            "#C0392B"
          ],
          [
            "0.69 (RED)",
            "#C0392B"
          ]
        ],
        "VSI mean": [
          [
            "28.0 V",
            "#27AE60"
          ],
          [
            "27.9 V",
            "#27AE60"
          ],
          [
            "27.8 V",
            "#27AE60"
          ],
          [
            "28.2 V",
            "#27AE60"
          ],
          [
            "27.8 V",
            "#27AE60"
          ]
        ],
        "Resting V": [
          [
            "26.0 V",
            "#F5A623"
          ],
          [
            "25.6 V",
            "#C0392B"
          ],
          [
            "23.7 V",
            "#C0392B"
          ],
          [
            "24.2 V",
            "#C0392B"
          ],
          [
            "24.2 V",
            "#C0392B"
          ]
        ],
        "Sag rate": [
          [
            "0.00",
            "#F5A623"
          ],
          [
            "0.00",
            "#27AE60"
          ],
          [
            "0.00",
            "#F5A623"
          ],
          [
            "0.00",
            "#F5A623"
          ],
          [
            "0.00",
            "#F5A623"
          ]
        ],
        "Crank-recovery": [
          [
            "-0.2\u03c3",
            "#27AE60"
          ],
          [
            "-0.2\u03c3",
            "#27AE60"
          ],
          [
            "-0.2\u03c3",
            "#27AE60"
          ],
          [
            "-0.2\u03c3",
            "#27AE60"
          ],
          [
            "-0.2\u03c3",
            "#27AE60"
          ]
        ],
        "Reg. ceiling": [
          [
            "-0.3\u03c3",
            "#27AE60"
          ],
          [
            "-0.2\u03c3",
            "#27AE60"
          ],
          [
            "-1.5\u03c3",
            "#27AE60"
          ],
          [
            "-1.5\u03c3",
            "#27AE60"
          ],
          [
            "-1.8\u03c3",
            "#27AE60"
          ]
        ],
        "GED2": [
          [
            "\u2014",
            "#ECEFF1"
          ],
          [
            "\u2014",
            "#ECEFF1"
          ],
          [
            "\u2014",
            "#ECEFF1"
          ],
          [
            "STORM",
            "#C0392B"
          ],
          [
            "\u2014",
            "#ECEFF1"
          ]
        ]
      },
      "charge": [
        {
          "early": [
            "[ 650.  750.  850.  950. 1050. 1150. 1250. 1350. 1450. 1550. 1650. 1750.\n 1850. 1950. 2050. 2150. 2250. 2350. 2450.]",
            "[28. 28. 28. 28. 28. 28. 28. 28. 28. 28. 28. 28. 28. 28. 28. 28. 28. 28.\n 28.]"
          ],
          "late": [
            "[ 650.  750.  850.  950. 1050. 1150. 1250. 1350. 1450. 1550. 1650. 1750.\n 1850. 1950. 2050. 2150. 2250. 2350. 2450.]",
            "[28.         28.         28.         28.         28.20000076 28.20000076\n 28.20000076 28.20000076 28.20000076 28.20000076 28.20000076 28.20000076\n 28.20000076 28.20000076 28.20000076 28.20000076 28.20000076 28.20000076\n 28.20000076]"
          ]
        }
      ],
      "risk": "red",
      "dname": "VIN1_F_ALT"
    }
  },
  {
    "vin": "VIN2_F_ALT",
    "dname": "VIN2_F_ALT",
    "failed": true,
    "risk_band": "red",
    "est_km": 104472.74,
    "median_rul": 0.0,
    "fw_p25": 577.5,
    "fw_p75": 652.5,
    "fleet_med": 601.0,
    "rul_last": 157.87188915396922,
    "clock_zone_last": "YELLOW",
    "gap": 0,
    "over_pred": 157.87188915396922,
    "m5_trans": [
      [
        "Nov 2025",
        "YELLOW",
        "VSI volatility"
      ],
      [
        "Dec 2025",
        "ORANGE",
        "VSI volatility"
      ]
    ],
    "m5_final": "ORANGE",
    "m5_peak": null,
    "breaches": [
      [
        "under-voltage sag",
        16
      ],
      [
        "regulation ceiling",
        15
      ],
      [
        "voltage residual",
        15
      ]
    ],
    "ged": false,
    "ged_lead": null,
    "cdelta": 0.20000076293945312,
    "n_cross": 1,
    "cross": [
      [
        "GREEN\u2192YELLOW",
        false,
        null
      ]
    ],
    "arch": "Late precursor: under-voltage sag (~16d)",
    "snap": {
      "cols": [
        [
          "Early",
          "2024-05-28 00:00:00"
        ],
        [
          "First deviation",
          "2025-11-30 00:00:00"
        ],
        [
          "Cond\u2192ORANGE",
          "2025-12-09 00:00:00"
        ],
        [
          "Failure",
          "2025-12-16 00:00:00"
        ]
      ],
      "col_index": {
        "Early": 0,
        "First deviation": 1,
        "Cond\u2192ORANGE": 2,
        "Failure": 3
      },
      "rows": {
        "Effective zone": [
          [
            "GREEN",
            "#27AE60"
          ],
          [
            "YELLOW",
            "#F5A623"
          ],
          [
            "YELLOW",
            "#F5A623"
          ],
          [
            "YELLOW",
            "#F5A623"
          ]
        ],
        "RUL (schedule)": [
          [
            "664 d (GREEN)",
            "#27AE60"
          ],
          [
            "161 d (YELLOW)",
            "#F5A623"
          ],
          [
            "159 d (YELLOW)",
            "#F5A623"
          ],
          [
            "158 d (YELLOW)",
            "#F5A623"
          ]
        ],
        "Condition (M5)": [
          [
            "0.09 (GREEN)",
            "#27AE60"
          ],
          [
            "0.15 (YELLOW)",
            "#F5A623"
          ],
          [
            "0.35 (ORANGE)",
            "#E67E22"
          ],
          [
            "0.41 (ORANGE)",
            "#E67E22"
          ]
        ],
        "VSI mean": [
          [
            "28.1 V",
            "#27AE60"
          ],
          [
            "28.1 V",
            "#27AE60"
          ],
          [
            "28.0 V",
            "#27AE60"
          ],
          [
            "28.2 V",
            "#27AE60"
          ]
        ],
        "Resting V": [
          [
            "24.8 V",
            "#C0392B"
          ],
          [
            "nan V",
            "#27AE60"
          ],
          [
            "nan V",
            "#27AE60"
          ],
          [
            "nan V",
            "#27AE60"
          ]
        ],
        "Sag rate": [
          [
            "0.00",
            "#27AE60"
          ],
          [
            "0.00",
            "#27AE60"
          ],
          [
            "0.00",
            "#27AE60"
          ],
          [
            "0.00",
            "#27AE60"
          ]
        ],
        "Crank-recovery": [
          [
            "-0.1\u03c3",
            "#27AE60"
          ],
          [
            "-0.1\u03c3",
            "#27AE60"
          ],
          [
            "-0.1\u03c3",
            "#27AE60"
          ],
          [
            "-0.1\u03c3",
            "#27AE60"
          ]
        ],
        "Reg. ceiling": [
          [
            "-0.2\u03c3",
            "#27AE60"
          ],
          [
            "+1.0\u03c3",
            "#F5A623"
          ],
          [
            "+3.2\u03c3",
            "#C0392B"
          ],
          [
            "+4.8\u03c3",
            "#C0392B"
          ]
        ],
        "GED2": [
          [
            "\u2014",
            "#ECEFF1"
          ],
          [
            "\u2014",
            "#ECEFF1"
          ],
          [
            "\u2014",
            "#ECEFF1"
          ],
          [
            "\u2014",
            "#ECEFF1"
          ]
        ]
      },
      "charge": [
        {
          "early": [
            "[ 650.  750.  850.  950. 1050. 1150. 1250. 1350. 1450. 1550. 1650. 1750.\n 1850. 1950. 2050. 2150. 2250. 2350. 2450.]",
            "[28.20000076 28.         28.         28.         28.         28.\n 28.         28.         28.         28.         28.         28.\n 28.         28.         28.         28.         28.         28.\n 28.        ]"
          ],
          "late": [
            "[ 650.  750.  850.  950. 1050. 1150. 1250. 1350. 1450. 1550. 1650. 1750.\n 1850. 1950. 2050. 2150. 2250. 2350. 2450.]",
            "[28.         28.         28.         28.         28.         28.\n 28.         28.         28.         28.         28.         28.\n 28.         28.20000076 28.20000076 28.20000076 28.20000076 28.20000076\n 28.20000076]"
          ]
        }
      ],
      "risk": "red",
      "dname": "VIN2_F_ALT"
    }
  },
  {
    "vin": "VIN3_F_ALT",
    "dname": "VIN3_F_ALT",
    "failed": true,
    "risk_band": "red",
    "est_km": 152634.34,
    "median_rul": 0.0,
    "fw_p25": 577.5,
    "fw_p75": 652.5,
    "fleet_med": 601.0,
    "rul_last": 177.93559016807558,
    "clock_zone_last": "YELLOW",
    "gap": 66,
    "over_pred": 111.93559016807558,
    "m5_trans": [],
    "m5_final": "GREEN",
    "m5_peak": "YELLOW",
    "breaches": [],
    "ged": false,
    "ged_lead": null,
    "cdelta": 0.0,
    "n_cross": 1,
    "cross": [
      [
        "GREEN\u2192YELLOW",
        false,
        null
      ]
    ],
    "arch": "Silent / abrupt failure",
    "snap": {
      "cols": [
        [
          "Early",
          "2024-04-14 00:00:00"
        ],
        [
          "Failure",
          "2025-12-02 00:00:00"
        ]
      ],
      "col_index": {
        "Early": 0,
        "Failure": 1
      },
      "rows": {
        "Effective zone": [
          [
            "GREEN",
            "#27AE60"
          ],
          [
            "YELLOW",
            "#F5A623"
          ]
        ],
        "RUL (schedule)": [
          [
            "661 d (GREEN)",
            "#27AE60"
          ],
          [
            "178 d (YELLOW)",
            "#F5A623"
          ]
        ],
        "Condition (M5)": [
          [
            "0.13 (GREEN)",
            "#27AE60"
          ],
          [
            "0.12 (GREEN)",
            "#27AE60"
          ]
        ],
        "VSI mean": [
          [
            "27.9 V",
            "#27AE60"
          ],
          [
            "27.9 V",
            "#27AE60"
          ]
        ],
        "Resting V": [
          [
            "23.6 V",
            "#C0392B"
          ],
          [
            "nan V",
            "#27AE60"
          ]
        ],
        "Sag rate": [
          [
            "0.00",
            "#27AE60"
          ],
          [
            "0.00",
            "#27AE60"
          ]
        ],
        "Crank-recovery": [
          [
            "-0.2\u03c3",
            "#27AE60"
          ],
          [
            "+0.8\u03c3",
            "#27AE60"
          ]
        ],
        "Reg. ceiling": [
          [
            "+0.2\u03c3",
            "#27AE60"
          ],
          [
            "-0.1\u03c3",
            "#27AE60"
          ]
        ],
        "GED2": [
          [
            "\u2014",
            "#ECEFF1"
          ],
          [
            "\u2014",
            "#ECEFF1"
          ]
        ]
      },
      "charge": [
        {
          "early": [
            "[ 650.  750.  850.  950. 1050. 1150. 1250. 1350. 1450. 1550. 1650. 1750.\n 1850. 1950. 2050. 2150. 2250. 2350.]",
            "[28.         28.         28.         28.         28.         28.\n 28.         28.         28.         28.         28.         28.\n 28.         28.         27.79999924 28.         27.79999924 27.79999924]"
          ],
          "late": [
            "[ 650.  750.  850.  950. 1050. 1150. 1250. 1350. 1450. 1550. 1650. 1750.\n 1850. 1950. 2050. 2150. 2350.]",
            "[28. 28. 28. 28. 28. 28. 28. 28. 28. 28. 28. 28. 28. 28. 28. 28. 28.]"
          ]
        }
      ],
      "risk": "red",
      "dname": "VIN3_F_ALT"
    }
  },
  {
    "vin": "VIN4_F_ALT",
    "dname": "VIN4_F_ALT",
    "failed": true,
    "risk_band": "amber",
    "est_km": 115517.38,
    "median_rul": 0.0,
    "fw_p25": 577.5,
    "fw_p75": 652.5,
    "fleet_med": 601.0,
    "rul_last": 133.1558865220943,
    "clock_zone_last": "YELLOW",
    "gap": 0,
    "over_pred": 133.1558865220943,
    "m5_trans": [
      [
        "Jun 2024",
        "YELLOW",
        "VSI volatility"
      ]
    ],
    "m5_final": "YELLOW",
    "m5_peak": null,
    "breaches": [],
    "ged": false,
    "ged_lead": null,
    "cdelta": 0.0,
    "n_cross": 1,
    "cross": [
      [
        "GREEN\u2192YELLOW",
        false,
        null
      ]
    ],
    "arch": "Silent / abrupt failure",
    "snap": {
      "cols": [
        [
          "Early",
          "2024-03-31 00:00:00"
        ],
        [
          "Failure",
          "2025-11-25 00:00:00"
        ]
      ],
      "col_index": {
        "Early": 0,
        "Failure": 1
      },
      "rows": {
        "Effective zone": [
          [
            "YELLOW",
            "#F5A623"
          ],
          [
            "YELLOW",
            "#F5A623"
          ]
        ],
        "RUL (schedule)": [
          [
            "662 d (GREEN)",
            "#27AE60"
          ],
          [
            "133 d (YELLOW)",
            "#F5A623"
          ]
        ],
        "Condition (M5)": [
          [
            "0.18 (YELLOW)",
            "#F5A623"
          ],
          [
            "0.23 (YELLOW)",
            "#F5A623"
          ]
        ],
        "VSI mean": [
          [
            "27.9 V",
            "#27AE60"
          ],
          [
            "28.4 V",
            "#27AE60"
          ]
        ],
        "Resting V": [
          [
            "23.2 V",
            "#C0392B"
          ],
          [
            "24.4 V",
            "#C0392B"
          ]
        ],
        "Sag rate": [
          [
            "0.00",
            "#27AE60"
          ],
          [
            "0.00",
            "#F5A623"
          ]
        ],
        "Crank-recovery": [
          [
            "-0.1\u03c3",
            "#27AE60"
          ],
          [
            "-0.1\u03c3",
            "#27AE60"
          ]
        ],
        "Reg. ceiling": [
          [
            "-0.3\u03c3",
            "#27AE60"
          ],
          [
            "-0.2\u03c3",
            "#27AE60"
          ]
        ],
        "GED2": [
          [
            "\u2014",
            "#ECEFF1"
          ],
          [
            "\u2014",
            "#ECEFF1"
          ]
        ]
      },
      "charge": [
        {
          "early": [
            "[ 650.  750.  850.  950. 1050. 1150. 1250. 1350. 1450. 1550. 1650. 1750.\n 1850. 1950. 2050. 2150. 2250. 2350. 2450.]",
            "[28. 28. 28. 28. 28. 28. 28. 28. 28. 28. 28. 28. 28. 28. 28. 28. 28. 28.\n 28.]"
          ],
          "late": [
            "[ 650.  750.  850.  950. 1050. 1150. 1250. 1350. 1450. 1550. 1650. 1750.\n 1850. 1950. 2050. 2150. 2250. 2350. 2450.]",
            "[28. 28. 28. 28. 28. 28. 28. 28. 28. 28. 28. 28. 28. 28. 28. 28. 28. 28.\n 28.]"
          ]
        }
      ],
      "risk": "amber",
      "dname": "VIN4_F_ALT"
    }
  },
  {
    "vin": "VIN5_F_ALT",
    "dname": "VIN5_F_ALT",
    "failed": true,
    "risk_band": "green",
    "est_km": 108462.41,
    "median_rul": 0.0,
    "fw_p25": 577.5,
    "fw_p75": 652.5,
    "fleet_med": 601.0,
    "rul_last": 134.8624762574911,
    "clock_zone_last": "YELLOW",
    "gap": 0,
    "over_pred": 134.8624762574911,
    "m5_trans": [],
    "m5_final": "GREEN",
    "m5_peak": null,
    "breaches": [],
    "ged": false,
    "ged_lead": null,
    "cdelta": 0.0,
    "n_cross": 1,
    "cross": [
      [
        "GREEN\u2192YELLOW",
        false,
        null
      ]
    ],
    "arch": "Silent / abrupt failure",
    "snap": {
      "cols": [
        [
          "Early",
          "2024-03-31 00:00:00"
        ],
        [
          "Failure",
          "2025-11-22 00:00:00"
        ]
      ],
      "col_index": {
        "Early": 0,
        "Failure": 1
      },
      "rows": {
        "Effective zone": [
          [
            "GREEN",
            "#27AE60"
          ],
          [
            "YELLOW",
            "#F5A623"
          ]
        ],
        "RUL (schedule)": [
          [
            "663 d (GREEN)",
            "#27AE60"
          ],
          [
            "135 d (YELLOW)",
            "#F5A623"
          ]
        ],
        "Condition (M5)": [
          [
            "0.09 (GREEN)",
            "#27AE60"
          ],
          [
            "0.09 (GREEN)",
            "#27AE60"
          ]
        ],
        "VSI mean": [
          [
            "28.0 V",
            "#27AE60"
          ],
          [
            "28.0 V",
            "#27AE60"
          ]
        ],
        "Resting V": [
          [
            "24.7 V",
            "#C0392B"
          ],
          [
            "24.8 V",
            "#C0392B"
          ]
        ],
        "Sag rate": [
          [
            "0.00",
            "#F5A623"
          ],
          [
            "0.00",
            "#27AE60"
          ]
        ],
        "Crank-recovery": [
          [
            "+0.1\u03c3",
            "#27AE60"
          ],
          [
            "-0.1\u03c3",
            "#27AE60"
          ]
        ],
        "Reg. ceiling": [
          [
            "+0.0\u03c3",
            "#27AE60"
          ],
          [
            "-0.4\u03c3",
            "#27AE60"
          ]
        ],
        "GED2": [
          [
            "\u2014",
            "#ECEFF1"
          ],
          [
            "\u2014",
            "#ECEFF1"
          ]
        ]
      },
      "charge": [
        {
          "early": [
            "[ 650.  750.  850.  950. 1050. 1150. 1250. 1350. 1450. 1550. 1650. 1750.\n 1850. 1950. 2050. 2150. 2250. 2350. 2450.]",
            "[28. 28. 28. 28. 28. 28. 28. 28. 28. 28. 28. 28. 28. 28. 28. 28. 28. 28.\n 28.]"
          ],
          "late": [
            "[ 650.  750.  850.  950. 1050. 1150. 1250. 1350. 1450. 1550. 1650. 1750.\n 1850. 1950. 2050. 2150. 2250. 2350.]",
            "[28. 28. 28. 28. 28. 28. 28. 28. 28. 28. 28. 28. 28. 28. 28. 28. 28. 28.]"
          ]
        }
      ],
      "risk": "green",
      "dname": "VIN5_F_ALT"
    }
  },
  {
    "vin": "VIN6_F_ALT",
    "dname": "VIN6_F_ALT",
    "failed": true,
    "risk_band": "red",
    "est_km": 119166.2,
    "median_rul": 0.0,
    "fw_p25": 577.5,
    "fw_p75": 652.5,
    "fleet_med": 601.0,
    "rul_last": 204.70522014286126,
    "clock_zone_last": "GREEN",
    "gap": 0,
    "over_pred": 204.70522014286126,
    "m5_trans": [],
    "m5_final": "GREEN",
    "m5_peak": "YELLOW",
    "breaches": [
      [
        "crank-recovery t",
        11
      ]
    ],
    "ged": false,
    "ged_lead": null,
    "cdelta": 0.0,
    "n_cross": 0,
    "cross": [],
    "arch": "Late precursor: crank-recovery t (~11d)",
    "snap": {
      "cols": [
        [
          "Early",
          "2024-05-26 00:00:00"
        ],
        [
          "First deviation",
          "2025-09-19 00:00:00"
        ],
        [
          "Failure",
          "2025-09-30 00:00:00"
        ]
      ],
      "col_index": {
        "Early": 0,
        "First deviation": 1,
        "Failure": 2
      },
      "rows": {
        "Effective zone": [
          [
            "GREEN",
            "#27AE60"
          ],
          [
            "GREEN",
            "#27AE60"
          ],
          [
            "GREEN",
            "#27AE60"
          ]
        ],
        "RUL (schedule)": [
          [
            "663 d (GREEN)",
            "#27AE60"
          ],
          [
            "213 d (GREEN)",
            "#27AE60"
          ],
          [
            "205 d (GREEN)",
            "#27AE60"
          ]
        ],
        "Condition (M5)": [
          [
            "0.07 (GREEN)",
            "#27AE60"
          ],
          [
            "0.11 (GREEN)",
            "#27AE60"
          ],
          [
            "0.14 (GREEN)",
            "#27AE60"
          ]
        ],
        "VSI mean": [
          [
            "28.1 V",
            "#27AE60"
          ],
          [
            "28.1 V",
            "#27AE60"
          ],
          [
            "28.2 V",
            "#27AE60"
          ]
        ],
        "Resting V": [
          [
            "24.9 V",
            "#C0392B"
          ],
          [
            "24.4 V",
            "#C0392B"
          ],
          [
            "22.5 V",
            "#C0392B"
          ]
        ],
        "Sag rate": [
          [
            "0.00",
            "#F5A623"
          ],
          [
            "0.00",
            "#27AE60"
          ],
          [
            "0.00",
            "#27AE60"
          ]
        ],
        "Crank-recovery": [
          [
            "+0.8\u03c3",
            "#27AE60"
          ],
          [
            "+29.1\u03c3",
            "#C0392B"
          ],
          [
            "+39.1\u03c3",
            "#C0392B"
          ]
        ],
        "Reg. ceiling": [
          [
            "+0.8\u03c3",
            "#27AE60"
          ],
          [
            "+1.4\u03c3",
            "#F5A623"
          ],
          [
            "+0.2\u03c3",
            "#27AE60"
          ]
        ],
        "GED2": [
          [
            "\u2014",
            "#ECEFF1"
          ],
          [
            "\u2014",
            "#ECEFF1"
          ],
          [
            "\u2014",
            "#ECEFF1"
          ]
        ]
      },
      "charge": [
        {
          "early": [
            "[ 650.  750.  850.  950. 1050. 1150. 1250. 1350. 1450. 1550. 1650. 1750.\n 1850. 1950. 2050. 2150. 2250. 2350. 2450.]",
            "[28.20000076 28.20000076 28.20000076 28.20000076 28.20000076 28.20000076\n 28.20000076 28.20000076 28.20000076 28.20000076 28.20000076 28.20000076\n 28.20000076 28.20000076 28.20000076 28.20000076 28.20000076 28.20000076\n 28.20000076]"
          ],
          "late": [
            "[ 650.  750.  850.  950. 1050. 1150. 1250. 1350. 1450. 1550. 1650. 1750.\n 1850. 1950. 2050. 2150. 2250. 2350. 2450.]",
            "[28.20000076 28.20000076 28.20000076 28.20000076 28.20000076 28.20000076\n 28.20000076 28.20000076 28.20000076 28.20000076 28.20000076 28.20000076\n 28.20000076 28.20000076 28.20000076 28.20000076 28.20000076 28.20000076\n 28.20000076]"
          ]
        }
      ],
      "risk": "red",
      "dname": "VIN6_F_ALT"
    }
  },
  {
    "vin": "VIN7_F_ALT",
    "dname": "VIN7_F_ALT",
    "failed": true,
    "risk_band": "red",
    "est_km": 112798.02,
    "median_rul": 0.0,
    "fw_p25": 577.5,
    "fw_p75": 652.5,
    "fleet_med": 601.0,
    "rul_last": 130.105967741384,
    "clock_zone_last": "YELLOW",
    "gap": 0,
    "over_pred": 130.105967741384,
    "m5_trans": [],
    "m5_final": "GREEN",
    "m5_peak": null,
    "breaches": [],
    "ged": false,
    "ged_lead": null,
    "cdelta": 0.0,
    "n_cross": 1,
    "cross": [
      [
        "GREEN\u2192YELLOW",
        false,
        null
      ]
    ],
    "arch": "Silent / abrupt failure",
    "snap": {
      "cols": [
        [
          "Early",
          "2024-03-31 00:00:00"
        ],
        [
          "Failure",
          "2025-12-04 00:00:00"
        ]
      ],
      "col_index": {
        "Early": 0,
        "Failure": 1
      },
      "rows": {
        "Effective zone": [
          [
            "GREEN",
            "#27AE60"
          ],
          [
            "YELLOW",
            "#F5A623"
          ]
        ],
        "RUL (schedule)": [
          [
            "663 d (GREEN)",
            "#27AE60"
          ],
          [
            "130 d (YELLOW)",
            "#F5A623"
          ]
        ],
        "Condition (M5)": [
          [
            "0.10 (GREEN)",
            "#27AE60"
          ],
          [
            "0.09 (GREEN)",
            "#27AE60"
          ]
        ],
        "VSI mean": [
          [
            "28.0 V",
            "#27AE60"
          ],
          [
            "28.0 V",
            "#27AE60"
          ]
        ],
        "Resting V": [
          [
            "25.0 V",
            "#C0392B"
          ],
          [
            "25.4 V",
            "#C0392B"
          ]
        ],
        "Sag rate": [
          [
            "0.00",
            "#27AE60"
          ],
          [
            "0.00",
            "#27AE60"
          ]
        ],
        "Crank-recovery": [
          [
            "-0.1\u03c3",
            "#27AE60"
          ],
          [
            "-0.1\u03c3",
            "#27AE60"
          ]
        ],
        "Reg. ceiling": [
          [
            "+0.1\u03c3",
            "#27AE60"
          ],
          [
            "+0.9\u03c3",
            "#27AE60"
          ]
        ],
        "GED2": [
          [
            "\u2014",
            "#ECEFF1"
          ],
          [
            "\u2014",
            "#ECEFF1"
          ]
        ]
      },
      "charge": [
        {
          "early": [
            "[ 650.  750.  850.  950. 1050. 1150. 1250. 1350. 1450. 1550. 1650. 1750.\n 1850. 1950. 2050. 2150. 2250. 2350. 2450.]",
            "[28.         28.         28.         28.         28.         28.\n 28.         28.         28.         28.         28.         28.\n 28.         28.         28.         28.         28.         28.10000038\n 28.        ]"
          ],
          "late": [
            "[ 650.  750.  850.  950. 1050. 1150. 1250. 1350. 1450. 1550. 1650. 1750.\n 1850. 1950. 2050. 2150. 2250. 2350. 2450.]",
            "[28. 28. 28. 28. 28. 28. 28. 28. 28. 28. 28. 28. 28. 28. 28. 28. 28. 28.\n 28.]"
          ]
        }
      ],
      "risk": "red",
      "dname": "VIN7_F_ALT"
    }
  },
  {
    "vin": "VIN8_F_ALT",
    "dname": "VIN8_F_ALT",
    "failed": true,
    "risk_band": "red",
    "est_km": 121845.69,
    "median_rul": 0.0,
    "fw_p25": 577.5,
    "fw_p75": 652.5,
    "fleet_med": 601.0,
    "rul_last": 189.25033025341463,
    "clock_zone_last": "GREEN",
    "gap": 0,
    "over_pred": 189.25033025341463,
    "m5_trans": [
      [
        "Sep 2024",
        "YELLOW",
        "VSI volatility"
      ]
    ],
    "m5_final": "YELLOW",
    "m5_peak": "ORANGE",
    "breaches": [],
    "ged": false,
    "ged_lead": null,
    "cdelta": 0.0,
    "n_cross": 0,
    "cross": [],
    "arch": "Silent / abrupt failure",
    "snap": {
      "cols": [
        [
          "Early",
          "2024-06-29 00:00:00"
        ],
        [
          "Cond\u2192ORANGE",
          "2024-10-10 00:00:00"
        ],
        [
          "Failure",
          "2025-11-24 00:00:00"
        ]
      ],
      "col_index": {
        "Early": 0,
        "Cond\u2192ORANGE": 1,
        "Failure": 2
      },
      "rows": {
        "Effective zone": [
          [
            "GREEN",
            "#27AE60"
          ],
          [
            "YELLOW",
            "#F5A623"
          ],
          [
            "YELLOW",
            "#F5A623"
          ]
        ],
        "RUL (schedule)": [
          [
            "663 d (GREEN)",
            "#27AE60"
          ],
          [
            "559 d (GREEN)",
            "#27AE60"
          ],
          [
            "189 d (GREEN)",
            "#27AE60"
          ]
        ],
        "Condition (M5)": [
          [
            "0.11 (GREEN)",
            "#27AE60"
          ],
          [
            "0.35 (ORANGE)",
            "#E67E22"
          ],
          [
            "0.21 (YELLOW)",
            "#F5A623"
          ]
        ],
        "VSI mean": [
          [
            "27.8 V",
            "#27AE60"
          ],
          [
            "27.9 V",
            "#27AE60"
          ],
          [
            "27.8 V",
            "#27AE60"
          ]
        ],
        "Resting V": [
          [
            "25.0 V",
            "#C0392B"
          ],
          [
            "26.8 V",
            "#F5A623"
          ],
          [
            "24.9 V",
            "#C0392B"
          ]
        ],
        "Sag rate": [
          [
            "0.00",
            "#27AE60"
          ],
          [
            "0.00",
            "#27AE60"
          ],
          [
            "0.00",
            "#27AE60"
          ]
        ],
        "Crank-recovery": [
          [
            "-0.2\u03c3",
            "#27AE60"
          ],
          [
            "-0.2\u03c3",
            "#27AE60"
          ],
          [
            "-0.4\u03c3",
            "#27AE60"
          ]
        ],
        "Reg. ceiling": [
          [
            "+0.3\u03c3",
            "#27AE60"
          ],
          [
            "-0.5\u03c3",
            "#27AE60"
          ],
          [
            "-0.4\u03c3",
            "#27AE60"
          ]
        ],
        "GED2": [
          [
            "\u2014",
            "#ECEFF1"
          ],
          [
            "\u2014",
            "#ECEFF1"
          ],
          [
            "\u2014",
            "#ECEFF1"
          ]
        ]
      },
      "charge": [
        {
          "early": [
            "[ 650.  750.  850.  950. 1050. 1150. 1250. 1350. 1450. 1550. 1650. 1750.\n 1850. 1950. 2050. 2150. 2250. 2350. 2450.]",
            "[27.79999924 27.79999924 27.79999924 27.79999924 27.79999924 27.79999924\n 27.79999924 27.79999924 27.79999924 27.79999924 27.79999924 27.79999924\n 27.79999924 27.79999924 27.79999924 27.79999924 27.79999924 27.79999924\n 27.79999924]"
          ],
          "late": [
            "[ 650.  750.  850.  950. 1050. 1150. 1250. 1350. 1450. 1550. 1650. 1750.\n 1850. 1950. 2050. 2150. 2250. 2350. 2450.]",
            "[27.79999924 27.79999924 27.79999924 27.79999924 27.79999924 27.79999924\n 27.79999924 27.79999924 27.79999924 27.79999924 27.79999924 27.79999924\n 27.79999924 27.79999924 27.79999924 27.79999924 27.79999924 27.79999924\n 27.79999924]"
          ]
        }
      ],
      "risk": "red",
      "dname": "VIN8_F_ALT"
    }
  },
  {
    "vin": "VIN9_F_ALT",
    "dname": "VIN9_F_ALT",
    "failed": true,
    "risk_band": "amber",
    "est_km": 172910.6,
    "median_rul": 0.0,
    "fw_p25": 577.5,
    "fw_p75": 652.5,
    "fleet_med": 601.0,
    "rul_last": 168.9109802817543,
    "clock_zone_last": "YELLOW",
    "gap": 2,
    "over_pred": 166.9109802817543,
    "m5_trans": [],
    "m5_final": "GREEN",
    "m5_peak": null,
    "breaches": [],
    "ged": false,
    "ged_lead": null,
    "cdelta": 0.0,
    "n_cross": 1,
    "cross": [
      [
        "GREEN\u2192YELLOW",
        false,
        null
      ]
    ],
    "arch": "Silent / abrupt failure",
    "snap": {
      "cols": [
        [
          "Early",
          "2024-06-29 00:00:00"
        ],
        [
          "Failure",
          "2025-12-29 00:00:00"
        ]
      ],
      "col_index": {
        "Early": 0,
        "Failure": 1
      },
      "rows": {
        "Effective zone": [
          [
            "GREEN",
            "#27AE60"
          ],
          [
            "YELLOW",
            "#F5A623"
          ]
        ],
        "RUL (schedule)": [
          [
            "663 d (GREEN)",
            "#27AE60"
          ],
          [
            "169 d (YELLOW)",
            "#F5A623"
          ]
        ],
        "Condition (M5)": [
          [
            "0.09 (GREEN)",
            "#27AE60"
          ],
          [
            "0.09 (GREEN)",
            "#27AE60"
          ]
        ],
        "VSI mean": [
          [
            "28.1 V",
            "#27AE60"
          ],
          [
            "28.2 V",
            "#27AE60"
          ]
        ],
        "Resting V": [
          [
            "24.3 V",
            "#C0392B"
          ],
          [
            "nan V",
            "#27AE60"
          ]
        ],
        "Sag rate": [
          [
            "0.00",
            "#27AE60"
          ],
          [
            "0.00",
            "#F5A623"
          ]
        ],
        "Crank-recovery": [
          [
            "-0.0\u03c3",
            "#27AE60"
          ],
          [
            "-0.1\u03c3",
            "#27AE60"
          ]
        ],
        "Reg. ceiling": [
          [
            "+0.4\u03c3",
            "#27AE60"
          ],
          [
            "-0.2\u03c3",
            "#27AE60"
          ]
        ],
        "GED2": [
          [
            "\u2014",
            "#ECEFF1"
          ],
          [
            "\u2014",
            "#ECEFF1"
          ]
        ]
      },
      "charge": [
        {
          "early": [
            "[ 650.  750.  850.  950. 1050. 1150. 1250. 1350. 1450. 1550. 1650. 1750.\n 1850. 1950. 2050. 2150. 2250. 2350. 2450.]",
            "[28.20000076 28.20000076 28.20000076 28.20000076 28.20000076 28.20000076\n 28.20000076 28.20000076 28.20000076 28.20000076 28.20000076 28.20000076\n 28.20000076 28.20000076 28.20000076 28.20000076 28.20000076 28.20000076\n 28.20000076]"
          ],
          "late": [
            "[ 650.  750.  850.  950. 1050. 1150. 1250. 1350. 1450. 1550. 1650. 1750.\n 1850. 1950. 2050. 2150. 2250. 2350. 2450.]",
            "[28.20000076 28.20000076 28.20000076 28.20000076 28.20000076 28.20000076\n 28.20000076 28.20000076 28.20000076 28.20000076 28.20000076 28.20000076\n 28.20000076 28.20000076 28.20000076 28.20000076 28.20000076 28.20000076\n 28.20000076]"
          ]
        }
      ],
      "risk": "amber",
      "dname": "VIN9_F_ALT"
    }
  },
  {
    "vin": "VIN10_F_ALT",
    "dname": "VIN10_F_ALT",
    "failed": true,
    "risk_band": "red",
    "est_km": 123992.53,
    "median_rul": 0.0,
    "fw_p25": 577.5,
    "fw_p75": 652.5,
    "fleet_med": 601.0,
    "rul_last": 268.47987094190347,
    "clock_zone_last": "GREEN",
    "gap": 0,
    "over_pred": 268.47987094190347,
    "m5_trans": [
      [
        "Dec 2025",
        "YELLOW",
        "VSI volatility"
      ],
      [
        "Dec 2025",
        "ORANGE",
        "VSI volatility"
      ]
    ],
    "m5_final": "ORANGE",
    "m5_peak": null,
    "breaches": [
      [
        "crank-recovery t",
        11
      ],
      [
        "under-voltage sag",
        11
      ]
    ],
    "ged": true,
    "ged_lead": 1,
    "cdelta": 0.0,
    "n_cross": 0,
    "cross": [],
    "arch": "Early-warning (GED2 storm ~1d)",
    "snap": {
      "cols": [
        [
          "Early",
          "2024-10-30 00:00:00"
        ],
        [
          "First deviation",
          "2025-12-05 00:00:00"
        ],
        [
          "Cond\u2192ORANGE",
          "2025-12-16 00:00:00"
        ],
        [
          "Failure",
          "2025-12-16 00:00:00"
        ]
      ],
      "col_index": {
        "Early": 0,
        "First deviation": 1,
        "Cond\u2192ORANGE": 2,
        "Failure": 3
      },
      "rows": {
        "Effective zone": [
          [
            "GREEN",
            "#27AE60"
          ],
          [
            "GREEN",
            "#27AE60"
          ],
          [
            "GREEN",
            "#27AE60"
          ],
          [
            "GREEN",
            "#27AE60"
          ]
        ],
        "RUL (schedule)": [
          [
            "663 d (GREEN)",
            "#27AE60"
          ],
          [
            "277 d (GREEN)",
            "#27AE60"
          ],
          [
            "268 d (GREEN)",
            "#27AE60"
          ],
          [
            "268 d (GREEN)",
            "#27AE60"
          ]
        ],
        "Condition (M5)": [
          [
            "0.07 (GREEN)",
            "#27AE60"
          ],
          [
            "0.23 (YELLOW)",
            "#F5A623"
          ],
          [
            "0.37 (ORANGE)",
            "#E67E22"
          ],
          [
            "0.37 (ORANGE)",
            "#E67E22"
          ]
        ],
        "VSI mean": [
          [
            "28.2 V",
            "#27AE60"
          ],
          [
            "28.2 V",
            "#27AE60"
          ],
          [
            "28.4 V",
            "#27AE60"
          ],
          [
            "28.4 V",
            "#27AE60"
          ]
        ],
        "Resting V": [
          [
            "nan V",
            "#27AE60"
          ],
          [
            "24.6 V",
            "#C0392B"
          ],
          [
            "24.8 V",
            "#C0392B"
          ],
          [
            "24.8 V",
            "#C0392B"
          ]
        ],
        "Sag rate": [
          [
            "0.00",
            "#27AE60"
          ],
          [
            "0.00",
            "#27AE60"
          ],
          [
            "0.00",
            "#F5A623"
          ],
          [
            "0.00",
            "#F5A623"
          ]
        ],
        "Crank-recovery": [
          [
            "-0.1\u03c3",
            "#27AE60"
          ],
          [
            "+1.7\u03c3",
            "#F5A623"
          ],
          [
            "+2.4\u03c3",
            "#C0392B"
          ],
          [
            "+2.4\u03c3",
            "#C0392B"
          ]
        ],
        "Reg. ceiling": [
          [
            "-0.2\u03c3",
            "#27AE60"
          ],
          [
            "+0.2\u03c3",
            "#27AE60"
          ],
          [
            "+0.7\u03c3",
            "#27AE60"
          ],
          [
            "+0.7\u03c3",
            "#27AE60"
          ]
        ],
        "GED2": [
          [
            "\u2014",
            "#ECEFF1"
          ],
          [
            "\u2014",
            "#ECEFF1"
          ],
          [
            "STORM",
            "#C0392B"
          ],
          [
            "STORM",
            "#C0392B"
          ]
        ]
      },
      "charge": [
        {
          "early": [
            "[ 650.  750.  850.  950. 1050. 1150. 1250. 1350. 1450. 1550. 1650. 1750.\n 1850. 1950. 2050. 2150. 2250. 2350. 2450.]",
            "[28.20000076 28.20000076 28.20000076 28.20000076 28.20000076 28.20000076\n 28.20000076 28.20000076 28.20000076 28.20000076 28.20000076 28.20000076\n 28.20000076 28.20000076 28.20000076 28.20000076 28.20000076 28.20000076\n 28.20000076]"
          ],
          "late": [
            "[ 650.  750.  850.  950. 1050. 1150. 1250. 1350. 1450. 1550. 1650. 1750.\n 1850. 1950. 2050. 2150. 2250. 2350. 2450.]",
            "[28.20000076 28.20000076 28.20000076 28.20000076 28.20000076 28.20000076\n 28.20000076 28.20000076 28.20000076 28.20000076 28.20000076 28.20000076\n 28.20000076 28.20000076 28.20000076 28.20000076 28.20000076 28.20000076\n 28.20000076]"
          ]
        }
      ],
      "risk": "red",
      "dname": "VIN10_F_ALT"
    }
  },
  {
    "vin": "VIN1_NF_ALT",
    "dname": "VIN11_NF_ALT",
    "failed": false,
    "risk_band": "green",
    "est_km": 122670.52,
    "median_rul": 97.3,
    "fw_p25": 577.5,
    "fw_p75": 652.5,
    "fleet_med": 601.0,
    "rul_last": 95.65312862405335,
    "clock_zone_last": "YELLOW",
    "gap": null,
    "over_pred": null,
    "m5_trans": [],
    "m5_final": "GREEN",
    "m5_peak": null,
    "breaches": [],
    "ged": false,
    "ged_lead": null,
    "cdelta": 0.20000076293945312,
    "n_cross": 1,
    "cross": [
      [
        "GREEN\u2192YELLOW",
        false,
        null
      ]
    ],
    "arch": "In-service \u2014 quiet",
    "snap": {
      "cols": [
        [
          "Early",
          "2024-04-02 00:00:00"
        ],
        [
          "Now",
          "2026-02-18 00:00:00"
        ]
      ],
      "col_index": {
        "Early": 0,
        "Now": 1
      },
      "rows": {
        "Effective zone": [
          [
            "GREEN",
            "#27AE60"
          ],
          [
            "YELLOW",
            "#F5A623"
          ]
        ],
        "RUL (schedule)": [
          [
            "663 d (GREEN)",
            "#27AE60"
          ],
          [
            "96 d (YELLOW)",
            "#F5A623"
          ]
        ],
        "Condition (M5)": [
          [
            "0.12 (GREEN)",
            "#27AE60"
          ],
          [
            "0.07 (GREEN)",
            "#27AE60"
          ]
        ],
        "VSI mean": [
          [
            "28.1 V",
            "#27AE60"
          ],
          [
            "28.2 V",
            "#27AE60"
          ]
        ],
        "Resting V": [
          [
            "24.8 V",
            "#C0392B"
          ],
          [
            "nan V",
            "#27AE60"
          ]
        ],
        "Sag rate": [
          [
            "0.00",
            "#27AE60"
          ],
          [
            "0.00",
            "#27AE60"
          ]
        ],
        "Crank-recovery": [
          [
            "-0.0\u03c3",
            "#27AE60"
          ],
          [
            "+0.9\u03c3",
            "#27AE60"
          ]
        ],
        "Reg. ceiling": [
          [
            "-0.6\u03c3",
            "#27AE60"
          ],
          [
            "-2.0\u03c3",
            "#27AE60"
          ]
        ],
        "GED2": [
          [
            "\u2014",
            "#ECEFF1"
          ],
          [
            "\u2014",
            "#ECEFF1"
          ]
        ]
      },
      "charge": [
        {
          "early": [
            "[ 650.  750.  850.  950. 1050. 1150. 1250. 1350. 1450. 1550. 1650. 1750.\n 1850. 1950. 2050. 2150. 2250. 2350. 2450.]",
            "[28. 28. 28. 28. 28. 28. 28. 28. 28. 28. 28. 28. 28. 28. 28. 28. 28. 28.\n 28.]"
          ],
          "late": [
            "[ 650.  750.  850.  950. 1050. 1150. 1250. 1350. 1450. 1550. 1650. 1750.\n 1850. 1950. 2050. 2150. 2250. 2350. 2450.]",
            "[28.20000076 28.20000076 28.20000076 28.20000076 28.20000076 28.20000076\n 28.20000076 28.20000076 28.20000076 28.20000076 28.20000076 28.20000076\n 28.20000076 28.20000076 28.20000076 28.20000076 28.20000076 28.20000076\n 28.20000076]"
          ]
        }
      ],
      "risk": "green",
      "dname": "VIN11_NF_ALT"
    }
  },
  {
    "vin": "VIN2_NF_ALT",
    "dname": "VIN12_NF_ALT",
    "failed": false,
    "risk_band": "amber",
    "est_km": 117538.55,
    "median_rul": 89.5,
    "fw_p25": 577.5,
    "fw_p75": 652.5,
    "fleet_med": 601.0,
    "rul_last": 90.16252786784077,
    "clock_zone_last": "YELLOW",
    "gap": null,
    "over_pred": null,
    "m5_trans": [],
    "m5_final": "GREEN",
    "m5_peak": "YELLOW",
    "breaches": [],
    "ged": false,
    "ged_lead": null,
    "cdelta": 0.20000076293945312,
    "n_cross": 1,
    "cross": [
      [
        "GREEN\u2192YELLOW",
        false,
        null
      ]
    ],
    "arch": "In-service \u2014 quiet",
    "snap": {
      "cols": [
        [
          "Early",
          "2024-03-22 00:00:00"
        ],
        [
          "Now",
          "2026-02-18 00:00:00"
        ]
      ],
      "col_index": {
        "Early": 0,
        "Now": 1
      },
      "rows": {
        "Effective zone": [
          [
            "GREEN",
            "#27AE60"
          ],
          [
            "YELLOW",
            "#F5A623"
          ]
        ],
        "RUL (schedule)": [
          [
            "663 d (GREEN)",
            "#27AE60"
          ],
          [
            "90 d (YELLOW)",
            "#F5A623"
          ]
        ],
        "Condition (M5)": [
          [
            "0.08 (GREEN)",
            "#27AE60"
          ],
          [
            "0.13 (GREEN)",
            "#27AE60"
          ]
        ],
        "VSI mean": [
          [
            "28.1 V",
            "#27AE60"
          ],
          [
            "28.1 V",
            "#27AE60"
          ]
        ],
        "Resting V": [
          [
            "24.4 V",
            "#C0392B"
          ],
          [
            "nan V",
            "#27AE60"
          ]
        ],
        "Sag rate": [
          [
            "0.00",
            "#27AE60"
          ],
          [
            "0.00",
            "#27AE60"
          ]
        ],
        "Crank-recovery": [
          [
            "-0.1\u03c3",
            "#27AE60"
          ],
          [
            "-0.1\u03c3",
            "#27AE60"
          ]
        ],
        "Reg. ceiling": [
          [
            "-1.1\u03c3",
            "#27AE60"
          ],
          [
            "-0.6\u03c3",
            "#27AE60"
          ]
        ],
        "GED2": [
          [
            "\u2014",
            "#ECEFF1"
          ],
          [
            "\u2014",
            "#ECEFF1"
          ]
        ]
      },
      "charge": [
        {
          "early": [
            "[ 650.  750.  850.  950. 1050. 1150. 1250. 1350. 1450. 1550. 1650. 1750.\n 1850. 1950. 2050. 2150. 2250. 2450.]",
            "[28. 28. 28. 28. 28. 28. 28. 28. 28. 28. 28. 28. 28. 28. 28. 28. 28. 28.]"
          ],
          "late": [
            "[ 650.  750.  850.  950. 1050. 1150. 1250. 1350. 1450. 1550. 1650. 1750.\n 1850. 1950. 2050. 2150. 2250. 2350. 2450.]",
            "[28.20000076 28.20000076 28.         28.         28.         28.\n 28.20000076 28.20000076 28.20000076 28.20000076 28.20000076 28.20000076\n 28.20000076 28.20000076 28.20000076 28.20000076 28.20000076 28.20000076\n 28.20000076]"
          ]
        }
      ],
      "risk": "amber",
      "dname": "VIN12_NF_ALT"
    }
  },
  {
    "vin": "VIN3_NF_ALT",
    "dname": "VIN13_NF_ALT",
    "failed": false,
    "risk_band": "amber",
    "est_km": 132387.34,
    "median_rul": 116.2,
    "fw_p25": 577.5,
    "fw_p75": 652.5,
    "fleet_med": 601.0,
    "rul_last": 120.5577360068832,
    "clock_zone_last": "YELLOW",
    "gap": null,
    "over_pred": null,
    "m5_trans": [],
    "m5_final": "GREEN",
    "m5_peak": "YELLOW",
    "breaches": [],
    "ged": false,
    "ged_lead": null,
    "cdelta": 0.0,
    "n_cross": 1,
    "cross": [
      [
        "GREEN\u2192YELLOW",
        false,
        null
      ]
    ],
    "arch": "In-service \u2014 quiet",
    "snap": {
      "cols": [
        [
          "Early",
          "2024-05-21 00:00:00"
        ],
        [
          "Now",
          "2026-02-13 00:00:00"
        ]
      ],
      "col_index": {
        "Early": 0,
        "Now": 1
      },
      "rows": {
        "Effective zone": [
          [
            "GREEN",
            "#27AE60"
          ],
          [
            "YELLOW",
            "#F5A623"
          ]
        ],
        "RUL (schedule)": [
          [
            "652 d (GREEN)",
            "#27AE60"
          ],
          [
            "121 d (YELLOW)",
            "#F5A623"
          ]
        ],
        "Condition (M5)": [
          [
            "0.13 (GREEN)",
            "#27AE60"
          ],
          [
            "0.11 (GREEN)",
            "#27AE60"
          ]
        ],
        "VSI mean": [
          [
            "27.9 V",
            "#27AE60"
          ],
          [
            "28.0 V",
            "#27AE60"
          ]
        ],
        "Resting V": [
          [
            "nan V",
            "#27AE60"
          ],
          [
            "26.1 V",
            "#F5A623"
          ]
        ],
        "Sag rate": [
          [
            "0.00",
            "#27AE60"
          ],
          [
            "0.00",
            "#27AE60"
          ]
        ],
        "Crank-recovery": [
          [
            "-0.1\u03c3",
            "#27AE60"
          ],
          [
            "-0.1\u03c3",
            "#27AE60"
          ]
        ],
        "Reg. ceiling": [
          [
            "+0.5\u03c3",
            "#27AE60"
          ],
          [
            "-0.6\u03c3",
            "#27AE60"
          ]
        ],
        "GED2": [
          [
            "\u2014",
            "#ECEFF1"
          ],
          [
            "\u2014",
            "#ECEFF1"
          ]
        ]
      },
      "charge": [
        {
          "early": [
            "[ 650.  750.  850.  950. 1050. 1150. 1250. 1350. 1450. 1550. 1650. 1750.\n 1850. 1950. 2050. 2150. 2250. 2350. 2450.]",
            "[28. 28. 28. 28. 28. 28. 28. 28. 28. 28. 28. 28. 28. 28. 28. 28. 28. 28.\n 28.]"
          ],
          "late": [
            "[ 650.  750.  850.  950. 1050. 1150. 1250. 1350. 1450. 1550. 1650. 1750.\n 1850. 1950. 2050. 2150. 2250. 2350. 2450.]",
            "[28. 28. 28. 28. 28. 28. 28. 28. 28. 28. 28. 28. 28. 28. 28. 28. 28. 28.\n 28.]"
          ]
        }
      ],
      "risk": "amber",
      "dname": "VIN13_NF_ALT"
    }
  },
  {
    "vin": "VIN4_NF_ALT",
    "dname": "VIN14_NF_ALT",
    "failed": false,
    "risk_band": "amber",
    "est_km": 104136.68,
    "median_rul": 123.5,
    "fw_p25": 577.5,
    "fw_p75": 652.5,
    "fleet_med": 601.0,
    "rul_last": 124.20498565098586,
    "clock_zone_last": "YELLOW",
    "gap": null,
    "over_pred": null,
    "m5_trans": [],
    "m5_final": "GREEN",
    "m5_peak": "YELLOW",
    "breaches": [],
    "ged": false,
    "ged_lead": null,
    "cdelta": 0.20000076293945312,
    "n_cross": 1,
    "cross": [
      [
        "GREEN\u2192YELLOW",
        false,
        null
      ]
    ],
    "arch": "In-service \u2014 quiet",
    "snap": {
      "cols": [
        [
          "Early",
          "2024-06-02 00:00:00"
        ],
        [
          "Now",
          "2026-02-17 00:00:00"
        ]
      ],
      "col_index": {
        "Early": 0,
        "Now": 1
      },
      "rows": {
        "Effective zone": [
          [
            "GREEN",
            "#27AE60"
          ],
          [
            "YELLOW",
            "#F5A623"
          ]
        ],
        "RUL (schedule)": [
          [
            "661 d (GREEN)",
            "#27AE60"
          ],
          [
            "124 d (YELLOW)",
            "#F5A623"
          ]
        ],
        "Condition (M5)": [
          [
            "0.12 (GREEN)",
            "#27AE60"
          ],
          [
            "0.12 (GREEN)",
            "#27AE60"
          ]
        ],
        "VSI mean": [
          [
            "28.0 V",
            "#27AE60"
          ],
          [
            "28.1 V",
            "#27AE60"
          ]
        ],
        "Resting V": [
          [
            "24.6 V",
            "#C0392B"
          ],
          [
            "24.4 V",
            "#C0392B"
          ]
        ],
        "Sag rate": [
          [
            "0.00",
            "#27AE60"
          ],
          [
            "0.00",
            "#27AE60"
          ]
        ],
        "Crank-recovery": [
          [
            "-0.1\u03c3",
            "#27AE60"
          ],
          [
            "-0.1\u03c3",
            "#27AE60"
          ]
        ],
        "Reg. ceiling": [
          [
            "+0.3\u03c3",
            "#27AE60"
          ],
          [
            "-0.3\u03c3",
            "#27AE60"
          ]
        ],
        "GED2": [
          [
            "\u2014",
            "#ECEFF1"
          ],
          [
            "\u2014",
            "#ECEFF1"
          ]
        ]
      },
      "charge": [
        {
          "early": [
            "[ 650.  750.  850.  950. 1050. 1150. 1250. 1350. 1450. 1550. 1650. 1750.\n 1850. 1950. 2050. 2150. 2250. 2350. 2450.]",
            "[28. 28. 28. 28. 28. 28. 28. 28. 28. 28. 28. 28. 28. 28. 28. 28. 28. 28.\n 28.]"
          ],
          "late": [
            "[ 650.  750.  850.  950. 1050. 1150. 1250. 1350. 1450. 1550. 1650. 1750.\n 1850. 1950. 2050. 2150. 2250. 2350. 2450.]",
            "[28.         28.20000076 28.20000076 28.20000076 28.20000076 28.20000076\n 28.20000076 28.20000076 28.20000076 28.20000076 28.20000076 28.20000076\n 28.20000076 28.20000076 28.20000076 28.20000076 28.20000076 28.20000076\n 28.20000076]"
          ]
        }
      ],
      "risk": "amber",
      "dname": "VIN14_NF_ALT"
    }
  },
  {
    "vin": "VIN5_NF_ALT",
    "dname": "VIN15_NF_ALT",
    "failed": false,
    "risk_band": "green",
    "est_km": 115156.59,
    "median_rul": 105.5,
    "fw_p25": 577.5,
    "fw_p75": 652.5,
    "fleet_med": 601.0,
    "rul_last": 106.72437311514165,
    "clock_zone_last": "YELLOW",
    "gap": null,
    "over_pred": null,
    "m5_trans": [],
    "m5_final": "GREEN",
    "m5_peak": "YELLOW",
    "breaches": [],
    "ged": false,
    "ged_lead": null,
    "cdelta": 0.20000076293945312,
    "n_cross": 1,
    "cross": [
      [
        "GREEN\u2192YELLOW",
        false,
        null
      ]
    ],
    "arch": "In-service \u2014 quiet",
    "snap": {
      "cols": [
        [
          "Early",
          "2024-04-28 00:00:00"
        ],
        [
          "Now",
          "2026-02-18 00:00:00"
        ]
      ],
      "col_index": {
        "Early": 0,
        "Now": 1
      },
      "rows": {
        "Effective zone": [
          [
            "GREEN",
            "#27AE60"
          ],
          [
            "YELLOW",
            "#F5A623"
          ]
        ],
        "RUL (schedule)": [
          [
            "663 d (GREEN)",
            "#27AE60"
          ],
          [
            "107 d (YELLOW)",
            "#F5A623"
          ]
        ],
        "Condition (M5)": [
          [
            "0.11 (GREEN)",
            "#27AE60"
          ],
          [
            "0.08 (GREEN)",
            "#27AE60"
          ]
        ],
        "VSI mean": [
          [
            "28.2 V",
            "#27AE60"
          ],
          [
            "28.2 V",
            "#27AE60"
          ]
        ],
        "Resting V": [
          [
            "nan V",
            "#27AE60"
          ],
          [
            "24.8 V",
            "#C0392B"
          ]
        ],
        "Sag rate": [
          [
            "0.00",
            "#27AE60"
          ],
          [
            "0.00",
            "#F5A623"
          ]
        ],
        "Crank-recovery": [
          [
            "-0.0\u03c3",
            "#27AE60"
          ],
          [
            "-0.1\u03c3",
            "#27AE60"
          ]
        ],
        "Reg. ceiling": [
          [
            "-1.1\u03c3",
            "#27AE60"
          ],
          [
            "-1.8\u03c3",
            "#27AE60"
          ]
        ],
        "GED2": [
          [
            "\u2014",
            "#ECEFF1"
          ],
          [
            "\u2014",
            "#ECEFF1"
          ]
        ]
      },
      "charge": [
        {
          "early": [
            "[ 650.  750.  850.  950. 1050. 1150. 1250. 1350. 1450. 1550. 1650. 1750.\n 1850. 1950. 2050. 2150. 2250. 2350. 2450.]",
            "[28. 28. 28. 28. 28. 28. 28. 28. 28. 28. 28. 28. 28. 28. 28. 28. 28. 28.\n 28.]"
          ],
          "late": [
            "[ 650.  750.  850.  950. 1050. 1150. 1250. 1350. 1450. 1550. 1650. 1750.\n 1850. 1950. 2050. 2150. 2250. 2350. 2450.]",
            "[28.20000076 28.20000076 28.20000076 28.20000076 28.20000076 28.20000076\n 28.20000076 28.20000076 28.20000076 28.20000076 28.20000076 28.20000076\n 28.20000076 28.20000076 28.20000076 28.20000076 28.20000076 28.20000076\n 28.20000076]"
          ]
        }
      ],
      "risk": "green",
      "dname": "VIN15_NF_ALT"
    }
  },
  {
    "vin": "VIN6_NF_ALT",
    "dname": "VIN16_NF_ALT",
    "failed": false,
    "risk_band": "amber",
    "est_km": 169535.28,
    "median_rul": 102.4,
    "fw_p25": 577.5,
    "fw_p75": 652.5,
    "fleet_med": 601.0,
    "rul_last": 102.8755090878438,
    "clock_zone_last": "YELLOW",
    "gap": null,
    "over_pred": null,
    "m5_trans": [],
    "m5_final": "GREEN",
    "m5_peak": "ORANGE",
    "breaches": [],
    "ged": false,
    "ged_lead": null,
    "cdelta": 0.0,
    "n_cross": 1,
    "cross": [
      [
        "GREEN\u2192YELLOW",
        false,
        null
      ]
    ],
    "arch": "In-service \u2014 quiet",
    "snap": {
      "cols": [
        [
          "Early",
          "2024-04-22 00:00:00"
        ],
        [
          "Cond\u2192ORANGE",
          "2024-05-15 00:00:00"
        ],
        [
          "Now",
          "2026-02-18 00:00:00"
        ]
      ],
      "col_index": {
        "Early": 0,
        "Cond\u2192ORANGE": 1,
        "Now": 2
      },
      "rows": {
        "Effective zone": [
          [
            "GREEN",
            "#27AE60"
          ],
          [
            "GREEN",
            "#27AE60"
          ],
          [
            "YELLOW",
            "#F5A623"
          ]
        ],
        "RUL (schedule)": [
          [
            "660 d (GREEN)",
            "#27AE60"
          ],
          [
            "638 d (GREEN)",
            "#27AE60"
          ],
          [
            "103 d (YELLOW)",
            "#F5A623"
          ]
        ],
        "Condition (M5)": [
          [
            "0.11 (GREEN)",
            "#27AE60"
          ],
          [
            "0.36 (ORANGE)",
            "#E67E22"
          ],
          [
            "0.09 (GREEN)",
            "#27AE60"
          ]
        ],
        "VSI mean": [
          [
            "27.8 V",
            "#27AE60"
          ],
          [
            "27.9 V",
            "#27AE60"
          ],
          [
            "27.9 V",
            "#27AE60"
          ]
        ],
        "Resting V": [
          [
            "24.7 V",
            "#C0392B"
          ],
          [
            "25.1 V",
            "#C0392B"
          ],
          [
            "nan V",
            "#27AE60"
          ]
        ],
        "Sag rate": [
          [
            "0.00",
            "#F5A623"
          ],
          [
            "0.00",
            "#F5A623"
          ],
          [
            "0.00",
            "#27AE60"
          ]
        ],
        "Crank-recovery": [
          [
            "-0.2\u03c3",
            "#27AE60"
          ],
          [
            "-0.0\u03c3",
            "#27AE60"
          ],
          [
            "-0.2\u03c3",
            "#27AE60"
          ]
        ],
        "Reg. ceiling": [
          [
            "+0.1\u03c3",
            "#27AE60"
          ],
          [
            "-1.1\u03c3",
            "#27AE60"
          ],
          [
            "-0.7\u03c3",
            "#27AE60"
          ]
        ],
        "GED2": [
          [
            "\u2014",
            "#ECEFF1"
          ],
          [
            "\u2014",
            "#ECEFF1"
          ],
          [
            "\u2014",
            "#ECEFF1"
          ]
        ]
      },
      "charge": [
        {
          "early": [
            "[ 650.  750.  850.  950. 1050. 1150. 1250. 1350. 1450. 1550. 1650. 1750.\n 1850. 1950. 2050. 2150. 2250.]",
            "[27.79999924 27.79999924 27.79999924 27.79999924 27.79999924 27.79999924\n 27.79999924 27.79999924 27.79999924 27.79999924 27.79999924 27.79999924\n 27.79999924 27.79999924 27.79999924 27.79999924 27.79999924]"
          ],
          "late": [
            "[ 650.  750.  850.  950. 1050. 1150. 1250. 1350. 1450. 1550. 1650. 1750.\n 1850. 1950. 2050. 2150. 2250.]",
            "[27.79999924 27.79999924 27.79999924 27.79999924 27.79999924 27.79999924\n 27.79999924 27.79999924 27.79999924 27.79999924 27.79999924 27.79999924\n 27.79999924 27.79999924 27.79999924 27.79999924 27.79999924]"
          ]
        }
      ],
      "risk": "amber",
      "dname": "VIN16_NF_ALT"
    }
  },
  {
    "vin": "VIN7_NF_ALT",
    "dname": "VIN17_NF_ALT",
    "failed": false,
    "risk_band": "amber",
    "est_km": 130094.06,
    "median_rul": 106.4,
    "fw_p25": 577.5,
    "fw_p75": 652.5,
    "fleet_med": 601.0,
    "rul_last": 109.41557261981194,
    "clock_zone_last": "YELLOW",
    "gap": null,
    "over_pred": null,
    "m5_trans": [],
    "m5_final": "GREEN",
    "m5_peak": "YELLOW",
    "breaches": [],
    "ged": false,
    "ged_lead": null,
    "cdelta": 0.0,
    "n_cross": 1,
    "cross": [
      [
        "GREEN\u2192YELLOW",
        false,
        null
      ]
    ],
    "arch": "In-service \u2014 quiet",
    "snap": {
      "cols": [
        [
          "Early",
          "2024-04-30 00:00:00"
        ],
        [
          "Now",
          "2026-02-18 00:00:00"
        ]
      ],
      "col_index": {
        "Early": 0,
        "Now": 1
      },
      "rows": {
        "Effective zone": [
          [
            "GREEN",
            "#27AE60"
          ],
          [
            "YELLOW",
            "#F5A623"
          ]
        ],
        "RUL (schedule)": [
          [
            "661 d (GREEN)",
            "#27AE60"
          ],
          [
            "109 d (YELLOW)",
            "#F5A623"
          ]
        ],
        "Condition (M5)": [
          [
            "0.10 (GREEN)",
            "#27AE60"
          ],
          [
            "0.12 (GREEN)",
            "#27AE60"
          ]
        ],
        "VSI mean": [
          [
            "27.9 V",
            "#27AE60"
          ],
          [
            "27.9 V",
            "#27AE60"
          ]
        ],
        "Resting V": [
          [
            "24.4 V",
            "#C0392B"
          ],
          [
            "nan V",
            "#27AE60"
          ]
        ],
        "Sag rate": [
          [
            "0.00",
            "#F5A623"
          ],
          [
            "0.00",
            "#27AE60"
          ]
        ],
        "Crank-recovery": [
          [
            "-0.1\u03c3",
            "#27AE60"
          ],
          [
            "+0.5\u03c3",
            "#27AE60"
          ]
        ],
        "Reg. ceiling": [
          [
            "-0.1\u03c3",
            "#27AE60"
          ],
          [
            "-0.8\u03c3",
            "#27AE60"
          ]
        ],
        "GED2": [
          [
            "\u2014",
            "#ECEFF1"
          ],
          [
            "\u2014",
            "#ECEFF1"
          ]
        ]
      },
      "charge": [
        {
          "early": [
            "[ 650.  750.  850.  950. 1050. 1150. 1250. 1350. 1450. 1550. 1650. 1750.\n 1850. 1950. 2050. 2150. 2250. 2350. 2450.]",
            "[27.79999924 28.         27.79999924 27.79999924 27.79999924 27.79999924\n 27.79999924 27.79999924 27.79999924 27.79999924 27.79999924 27.79999924\n 27.79999924 28.         28.         28.         28.         28.\n 28.        ]"
          ],
          "late": [
            "[ 650.  750.  850.  950. 1050. 1150. 1250. 1350. 1450. 1550. 1650. 1750.\n 1850. 1950. 2050. 2150. 2250. 2350. 2450.]",
            "[28. 28. 28. 28. 28. 28. 28. 28. 28. 28. 28. 28. 28. 28. 28. 28. 28. 28.\n 28.]"
          ]
        }
      ],
      "risk": "amber",
      "dname": "VIN17_NF_ALT"
    }
  },
  {
    "vin": "VIN8_NF_ALT",
    "dname": "VIN18_NF_ALT",
    "failed": false,
    "risk_band": "amber",
    "est_km": 114941.71,
    "median_rul": 234.5,
    "fw_p25": 577.5,
    "fw_p75": 652.5,
    "fleet_med": 601.0,
    "rul_last": 235.2507161521611,
    "clock_zone_last": "GREEN",
    "gap": null,
    "over_pred": null,
    "m5_trans": [
      [
        "Aug 2024",
        "YELLOW",
        "VSI volatility"
      ]
    ],
    "m5_final": "YELLOW",
    "m5_peak": null,
    "breaches": [],
    "ged": false,
    "ged_lead": null,
    "cdelta": 0.0,
    "n_cross": 0,
    "cross": [],
    "arch": "In-service \u2014 quiet",
    "snap": {
      "cols": [
        [
          "Early",
          "2024-02-29 00:00:00"
        ],
        [
          "Now",
          "2025-05-27 00:00:00"
        ]
      ],
      "col_index": {
        "Early": 0,
        "Now": 1
      },
      "rows": {
        "Effective zone": [
          [
            "YELLOW",
            "#F5A623"
          ],
          [
            "YELLOW",
            "#F5A623"
          ]
        ],
        "RUL (schedule)": [
          [
            "663 d (GREEN)",
            "#27AE60"
          ],
          [
            "235 d (GREEN)",
            "#27AE60"
          ]
        ],
        "Condition (M5)": [
          [
            "0.26 (YELLOW)",
            "#F5A623"
          ],
          [
            "0.21 (YELLOW)",
            "#F5A623"
          ]
        ],
        "VSI mean": [
          [
            "27.9 V",
            "#27AE60"
          ],
          [
            "28.0 V",
            "#27AE60"
          ]
        ],
        "Resting V": [
          [
            "25.7 V",
            "#C0392B"
          ],
          [
            "25.3 V",
            "#C0392B"
          ]
        ],
        "Sag rate": [
          [
            "0.01",
            "#F5A623"
          ],
          [
            "0.00",
            "#F5A623"
          ]
        ],
        "Crank-recovery": [
          [
            "+1.1\u03c3",
            "#F5A623"
          ],
          [
            "-0.2\u03c3",
            "#27AE60"
          ]
        ],
        "Reg. ceiling": [
          [
            "+0.0\u03c3",
            "#27AE60"
          ],
          [
            "-0.1\u03c3",
            "#27AE60"
          ]
        ],
        "GED2": [
          [
            "\u2014",
            "#ECEFF1"
          ],
          [
            "\u2014",
            "#ECEFF1"
          ]
        ]
      },
      "charge": [
        {
          "early": [
            "[ 650.  750.  850.  950. 1050. 1150. 1250. 1350. 1450. 1550. 1650. 1750.\n 1850. 1950. 2050. 2150. 2250. 2350. 2450.]",
            "[28.         28.         28.         28.         28.         28.\n 28.         28.         28.         28.         28.         28.\n 28.         28.         28.         28.         28.         28.20000076\n 28.20000076]"
          ],
          "late": [
            "[ 650.  750.  850.  950. 1050. 1150. 1250. 1350. 1450. 1550. 1650. 1750.\n 1850. 1950. 2050. 2150. 2250. 2350.]",
            "[28.         28.         28.         28.         28.         28.\n 28.         28.         28.         28.         28.         28.\n 28.         28.20000076 28.         28.20000076 28.20000076 28.20000076]"
          ]
        }
      ],
      "risk": "amber",
      "dname": "VIN18_NF_ALT"
    }
  },
  {
    "vin": "VIN9_NF_ALT",
    "dname": "VIN19_NF_ALT",
    "failed": false,
    "risk_band": "green",
    "est_km": 156358.18,
    "median_rul": 189.5,
    "fw_p25": 577.5,
    "fw_p75": 652.5,
    "fleet_med": 601.0,
    "rul_last": 186.04342515351118,
    "clock_zone_last": "GREEN",
    "gap": null,
    "over_pred": null,
    "m5_trans": [
      [
        "Jun 2024",
        "ORANGE",
        "VSI volatility"
      ]
    ],
    "m5_final": "ORANGE",
    "m5_peak": null,
    "breaches": [],
    "ged": false,
    "ged_lead": null,
    "cdelta": -0.1999988555908203,
    "n_cross": 0,
    "cross": [],
    "arch": "In-service \u2014 quiet",
    "snap": {
      "cols": [
        [
          "Cond\u2192ORANGE",
          "2024-01-01 00:00:00"
        ],
        [
          "Early",
          "2024-03-01 00:00:00"
        ],
        [
          "Now",
          "2025-07-28 00:00:00"
        ]
      ],
      "col_index": {
        "Cond\u2192ORANGE": 0,
        "Early": 1,
        "Now": 2
      },
      "rows": {
        "Effective zone": [
          [
            "GREEN",
            "#27AE60"
          ],
          [
            "ORANGE",
            "#E67E22"
          ],
          [
            "YELLOW",
            "#F5A623"
          ]
        ],
        "RUL (schedule)": [
          [
            "725 d (GREEN)",
            "#27AE60"
          ],
          [
            "663 d (GREEN)",
            "#27AE60"
          ],
          [
            "186 d (GREEN)",
            "#27AE60"
          ]
        ],
        "Condition (M5)": [
          [
            "0.36 (ORANGE)",
            "#E67E22"
          ],
          [
            "0.40 (ORANGE)",
            "#E67E22"
          ],
          [
            "0.36 (ORANGE)",
            "#E67E22"
          ]
        ],
        "VSI mean": [
          [
            "28.5 V",
            "#27AE60"
          ],
          [
            "28.5 V",
            "#27AE60"
          ],
          [
            "28.2 V",
            "#27AE60"
          ]
        ],
        "Resting V": [
          [
            "26.1 V",
            "#F5A623"
          ],
          [
            "24.7 V",
            "#C0392B"
          ],
          [
            "nan V",
            "#27AE60"
          ]
        ],
        "Sag rate": [
          [
            "0.00",
            "#27AE60"
          ],
          [
            "0.00",
            "#F5A623"
          ],
          [
            "0.00",
            "#27AE60"
          ]
        ],
        "Crank-recovery": [
          [
            "+1.5\u03c3",
            "#F5A623"
          ],
          [
            "+0.8\u03c3",
            "#27AE60"
          ],
          [
            "-0.1\u03c3",
            "#27AE60"
          ]
        ],
        "Reg. ceiling": [
          [
            "-0.2\u03c3",
            "#27AE60"
          ],
          [
            "-0.8\u03c3",
            "#27AE60"
          ],
          [
            "-0.1\u03c3",
            "#27AE60"
          ]
        ],
        "GED2": [
          [
            "\u2014",
            "#ECEFF1"
          ],
          [
            "\u2014",
            "#ECEFF1"
          ],
          [
            "\u2014",
            "#ECEFF1"
          ]
        ]
      },
      "charge": [
        {
          "early": [
            "[ 650.  750.  850.  950. 1050. 1150. 1250. 1350. 1450. 1550. 1650. 1750.\n 1850. 1950. 2050.]",
            "[28.39999962 28.39999962 28.39999962 28.39999962 28.39999962 28.39999962\n 28.39999962 28.39999962 28.39999962 28.39999962 28.39999962 28.39999962\n 28.39999962 28.39999962 28.39999962]"
          ],
          "late": [
            "[ 650.  750.  850.  950. 1050. 1150. 1250. 1350. 1450. 1550. 1650. 1750.\n 1850. 1950. 2050.]",
            "[28.20000076 28.20000076 28.20000076 28.20000076 28.20000076 28.20000076\n 28.20000076 28.20000076 28.20000076 28.20000076 28.20000076 28.20000076\n 28.20000076 28.20000076 28.39999962]"
          ]
        }
      ],
      "risk": "green",
      "dname": "VIN19_NF_ALT"
    }
  },
  {
    "vin": "VIN10_NF_ALT",
    "dname": "VIN20_NF_ALT",
    "failed": false,
    "risk_band": "amber",
    "est_km": 116797.86,
    "median_rul": 88.5,
    "fw_p25": 577.5,
    "fw_p75": 652.5,
    "fleet_med": 601.0,
    "rul_last": 91.7396656348248,
    "clock_zone_last": "YELLOW",
    "gap": null,
    "over_pred": null,
    "m5_trans": [],
    "m5_final": "GREEN",
    "m5_peak": "ORANGE",
    "breaches": [],
    "ged": false,
    "ged_lead": null,
    "cdelta": 0.10000038146972656,
    "n_cross": 1,
    "cross": [
      [
        "GREEN\u2192YELLOW",
        false,
        null
      ]
    ],
    "arch": "In-service \u2014 quiet",
    "snap": {
      "cols": [
        [
          "Early",
          "2024-03-19 00:00:00"
        ],
        [
          "Cond\u2192ORANGE",
          "2025-08-09 00:00:00"
        ],
        [
          "Now",
          "2026-02-18 00:00:00"
        ]
      ],
      "col_index": {
        "Early": 0,
        "Cond\u2192ORANGE": 1,
        "Now": 2
      },
      "rows": {
        "Effective zone": [
          [
            "GREEN",
            "#27AE60"
          ],
          [
            "YELLOW",
            "#F5A623"
          ],
          [
            "YELLOW",
            "#F5A623"
          ]
        ],
        "RUL (schedule)": [
          [
            "661 d (GREEN)",
            "#27AE60"
          ],
          [
            "190 d (GREEN)",
            "#27AE60"
          ],
          [
            "92 d (YELLOW)",
            "#F5A623"
          ]
        ],
        "Condition (M5)": [
          [
            "0.07 (GREEN)",
            "#27AE60"
          ],
          [
            "0.35 (ORANGE)",
            "#E67E22"
          ],
          [
            "0.10 (GREEN)",
            "#27AE60"
          ]
        ],
        "VSI mean": [
          [
            "28.4 V",
            "#27AE60"
          ],
          [
            "28.0 V",
            "#27AE60"
          ],
          [
            "28.1 V",
            "#27AE60"
          ]
        ],
        "Resting V": [
          [
            "nan V",
            "#27AE60"
          ],
          [
            "nan V",
            "#27AE60"
          ],
          [
            "nan V",
            "#27AE60"
          ]
        ],
        "Sag rate": [
          [
            "0.00",
            "#27AE60"
          ],
          [
            "0.00",
            "#27AE60"
          ],
          [
            "0.00",
            "#27AE60"
          ]
        ],
        "Crank-recovery": [
          [
            "-0.1\u03c3",
            "#27AE60"
          ],
          [
            "+0.7\u03c3",
            "#27AE60"
          ],
          [
            "-0.1\u03c3",
            "#27AE60"
          ]
        ],
        "Reg. ceiling": [
          [
            "-1.0\u03c3",
            "#27AE60"
          ],
          [
            "-1.2\u03c3",
            "#27AE60"
          ],
          [
            "-0.4\u03c3",
            "#27AE60"
          ]
        ],
        "GED2": [
          [
            "\u2014",
            "#ECEFF1"
          ],
          [
            "\u2014",
            "#ECEFF1"
          ],
          [
            "\u2014",
            "#ECEFF1"
          ]
        ]
      },
      "charge": [
        {
          "early": [
            "[ 650.  750.  850.  950. 1050. 1150. 1250. 1350. 1450. 1550. 1650. 1750.\n 1850. 1950. 2050. 2150. 2250. 2350. 2450.]",
            "[28.         28.20000076 28.         28.         28.         28.\n 28.         28.         28.         28.         28.         28.\n 28.         28.         28.         28.         28.         28.10000038\n 28.        ]"
          ],
          "late": [
            "[ 650.  750.  850.  950. 1050. 1150. 1250. 1350. 1450. 1550. 1650. 1750.\n 1850. 1950. 2050. 2150. 2250. 2350. 2450.]",
            "[28.         28.         28.         28.         28.         28.\n 28.         28.         28.         28.         28.         28.\n 28.         28.         28.20000076 28.20000076 28.20000076 28.20000076\n 28.20000076]"
          ]
        }
      ],
      "risk": "amber",
      "dname": "VIN20_NF_ALT"
    }
  },
  {
    "vin": "VIN11_NF_ALT",
    "dname": "VIN21_NF_ALT",
    "failed": false,
    "risk_band": "green",
    "est_km": 139904.19,
    "median_rul": 87.0,
    "fw_p25": 577.5,
    "fw_p75": 652.5,
    "fleet_med": 601.0,
    "rul_last": 88.02225135016164,
    "clock_zone_last": "ORANGE",
    "gap": null,
    "over_pred": null,
    "m5_trans": [],
    "m5_final": "GREEN",
    "m5_peak": "ORANGE",
    "breaches": [],
    "ged": false,
    "ged_lead": null,
    "cdelta": 0.0,
    "n_cross": 2,
    "cross": [
      [
        "GREEN\u2192YELLOW",
        false,
        null
      ],
      [
        "YELLOW\u2192ORANGE",
        false,
        null
      ]
    ],
    "arch": "In-service \u2014 quiet",
    "snap": {
      "cols": [
        [
          "Early",
          "2024-03-12 00:00:00"
        ],
        [
          "Cond\u2192ORANGE",
          "2025-08-29 00:00:00"
        ],
        [
          "Now",
          "2026-02-16 00:00:00"
        ]
      ],
      "col_index": {
        "Early": 0,
        "Cond\u2192ORANGE": 1,
        "Now": 2
      },
      "rows": {
        "Effective zone": [
          [
            "YELLOW",
            "#F5A623"
          ],
          [
            "ORANGE",
            "#E67E22"
          ],
          [
            "ORANGE",
            "#E67E22"
          ]
        ],
        "RUL (schedule)": [
          [
            "675 d (GREEN)",
            "#27AE60"
          ],
          [
            "174 d (YELLOW)",
            "#F5A623"
          ],
          [
            "88 d (ORANGE)",
            "#E67E22"
          ]
        ],
        "Condition (M5)": [
          [
            "0.29 (YELLOW)",
            "#F5A623"
          ],
          [
            "0.43 (ORANGE)",
            "#E67E22"
          ],
          [
            "0.08 (GREEN)",
            "#27AE60"
          ]
        ],
        "VSI mean": [
          [
            "28.1 V",
            "#27AE60"
          ],
          [
            "27.9 V",
            "#27AE60"
          ],
          [
            "28.3 V",
            "#27AE60"
          ]
        ],
        "Resting V": [
          [
            "nan V",
            "#27AE60"
          ],
          [
            "25.0 V",
            "#C0392B"
          ],
          [
            "25.2 V",
            "#C0392B"
          ]
        ],
        "Sag rate": [
          [
            "0.00",
            "#27AE60"
          ],
          [
            "0.00",
            "#27AE60"
          ],
          [
            "0.00",
            "#27AE60"
          ]
        ],
        "Crank-recovery": [
          [
            "-0.1\u03c3",
            "#27AE60"
          ],
          [
            "-0.1\u03c3",
            "#27AE60"
          ],
          [
            "-0.1\u03c3",
            "#27AE60"
          ]
        ],
        "Reg. ceiling": [
          [
            "-0.2\u03c3",
            "#27AE60"
          ],
          [
            "+1.3\u03c3",
            "#F5A623"
          ],
          [
            "-0.4\u03c3",
            "#27AE60"
          ]
        ],
        "GED2": [
          [
            "\u2014",
            "#ECEFF1"
          ],
          [
            "\u2014",
            "#ECEFF1"
          ],
          [
            "\u2014",
            "#ECEFF1"
          ]
        ]
      },
      "charge": [
        {
          "early": [
            "[ 650.  750.  850.  950. 1050. 1150. 1250. 1350.]",
            "[28.         28.         28.         28.         28.         28.\n 28.20000076 28.20000076]"
          ],
          "late": [
            "[ 650.  750.  850.  950. 1050. 1150. 1250. 1350. 1450. 1550. 1650. 1750.\n 1850. 1950. 2050. 2150. 2250. 2350. 2450.]",
            "[28.20000076 28.20000076 28.20000076 28.20000076 28.20000076 28.20000076\n 28.         28.         28.         28.         28.         28.\n 28.         28.         28.         28.         28.20000076 28.20000076\n 28.20000076]"
          ]
        }
      ],
      "risk": "green",
      "dname": "VIN21_NF_ALT"
    }
  },
  {
    "vin": "VIN12_NF_ALT",
    "dname": "VIN22_NF_ALT",
    "failed": false,
    "risk_band": "green",
    "est_km": 117417.7,
    "median_rul": 183.0,
    "fw_p25": 577.5,
    "fw_p75": 652.5,
    "fleet_med": 601.0,
    "rul_last": 185.152832927907,
    "clock_zone_last": "GREEN",
    "gap": null,
    "over_pred": null,
    "m5_trans": [],
    "m5_final": "GREEN",
    "m5_peak": "ORANGE",
    "breaches": [],
    "ged": false,
    "ged_lead": null,
    "cdelta": 0.20000076293945312,
    "n_cross": 0,
    "cross": [],
    "arch": "In-service \u2014 quiet",
    "snap": {
      "cols": [
        [
          "Early",
          "2024-09-15 00:00:00"
        ],
        [
          "Cond\u2192ORANGE",
          "2025-05-22 00:00:00"
        ],
        [
          "Now",
          "2026-02-18 00:00:00"
        ]
      ],
      "col_index": {
        "Early": 0,
        "Cond\u2192ORANGE": 1,
        "Now": 2
      },
      "rows": {
        "Effective zone": [
          [
            "GREEN",
            "#27AE60"
          ],
          [
            "YELLOW",
            "#F5A623"
          ],
          [
            "GREEN",
            "#27AE60"
          ]
        ],
        "RUL (schedule)": [
          [
            "644 d (GREEN)",
            "#27AE60"
          ],
          [
            "416 d (GREEN)",
            "#27AE60"
          ],
          [
            "185 d (GREEN)",
            "#27AE60"
          ]
        ],
        "Condition (M5)": [
          [
            "0.11 (GREEN)",
            "#27AE60"
          ],
          [
            "0.36 (ORANGE)",
            "#E67E22"
          ],
          [
            "0.11 (GREEN)",
            "#27AE60"
          ]
        ],
        "VSI mean": [
          [
            "27.9 V",
            "#27AE60"
          ],
          [
            "27.4 V",
            "#27AE60"
          ],
          [
            "28.0 V",
            "#27AE60"
          ]
        ],
        "Resting V": [
          [
            "24.4 V",
            "#C0392B"
          ],
          [
            "25.9 V",
            "#C0392B"
          ],
          [
            "25.3 V",
            "#C0392B"
          ]
        ],
        "Sag rate": [
          [
            "0.00",
            "#F5A623"
          ],
          [
            "0.00",
            "#F5A623"
          ],
          [
            "0.00",
            "#F5A623"
          ]
        ],
        "Crank-recovery": [
          [
            "-0.1\u03c3",
            "#27AE60"
          ],
          [
            "+1.0\u03c3",
            "#27AE60"
          ],
          [
            "-0.1\u03c3",
            "#27AE60"
          ]
        ],
        "Reg. ceiling": [
          [
            "-0.5\u03c3",
            "#27AE60"
          ],
          [
            "+1.8\u03c3",
            "#F5A623"
          ],
          [
            "-0.4\u03c3",
            "#27AE60"
          ]
        ],
        "GED2": [
          [
            "\u2014",
            "#ECEFF1"
          ],
          [
            "\u2014",
            "#ECEFF1"
          ],
          [
            "\u2014",
            "#ECEFF1"
          ]
        ]
      },
      "charge": [
        {
          "early": [
            "[ 650.  750.  850.  950. 1050. 1150. 1250. 1350. 1450. 1550. 1650. 1750.\n 1850.]",
            "[28.         28.         28.20000076 28.20000076 28.20000076 28.20000076\n 28.         28.         28.         28.         28.         28.\n 28.        ]"
          ],
          "late": [
            "[ 650.  750.  850.  950. 1050. 1150. 1250. 1350. 1450. 1550. 1650. 1750.\n 1850. 1950. 2050. 2150. 2350.]",
            "[28.         28.         28.         28.         28.         28.\n 28.         28.         28.         28.         28.20000076 28.20000076\n 28.20000076 28.20000076 28.20000076 28.20000076 28.20000076]"
          ]
        }
      ],
      "risk": "green",
      "dname": "VIN22_NF_ALT"
    }
  },
  {
    "vin": "VIN13_NF_ALT",
    "dname": "VIN23_NF_ALT",
    "failed": false,
    "risk_band": "green",
    "est_km": 117562.78,
    "median_rul": 118.4,
    "fw_p25": 577.5,
    "fw_p75": 652.5,
    "fleet_med": 601.0,
    "rul_last": 120.2211609849457,
    "clock_zone_last": "YELLOW",
    "gap": null,
    "over_pred": null,
    "m5_trans": [],
    "m5_final": "GREEN",
    "m5_peak": "YELLOW",
    "breaches": [],
    "ged": false,
    "ged_lead": null,
    "cdelta": 0.0,
    "n_cross": 1,
    "cross": [
      [
        "GREEN\u2192YELLOW",
        false,
        null
      ]
    ],
    "arch": "In-service \u2014 quiet",
    "snap": {
      "cols": [
        [
          "Early",
          "2024-05-21 00:00:00"
        ],
        [
          "Now",
          "2026-02-11 00:00:00"
        ]
      ],
      "col_index": {
        "Early": 0,
        "Now": 1
      },
      "rows": {
        "Effective zone": [
          [
            "YELLOW",
            "#F5A623"
          ],
          [
            "YELLOW",
            "#F5A623"
          ]
        ],
        "RUL (schedule)": [
          [
            "665 d (GREEN)",
            "#27AE60"
          ],
          [
            "120 d (YELLOW)",
            "#F5A623"
          ]
        ],
        "Condition (M5)": [
          [
            "0.18 (YELLOW)",
            "#F5A623"
          ],
          [
            "0.07 (GREEN)",
            "#27AE60"
          ]
        ],
        "VSI mean": [
          [
            "28.2 V",
            "#27AE60"
          ],
          [
            "28.2 V",
            "#27AE60"
          ]
        ],
        "Resting V": [
          [
            "nan V",
            "#27AE60"
          ],
          [
            "nan V",
            "#27AE60"
          ]
        ],
        "Sag rate": [
          [
            "0.00",
            "#27AE60"
          ],
          [
            "0.00",
            "#27AE60"
          ]
        ],
        "Crank-recovery": [
          [
            "-0.1\u03c3",
            "#27AE60"
          ],
          [
            "-0.1\u03c3",
            "#27AE60"
          ]
        ],
        "Reg. ceiling": [
          [
            "-0.7\u03c3",
            "#27AE60"
          ],
          [
            "+0.0\u03c3",
            "#27AE60"
          ]
        ],
        "GED2": [
          [
            "\u2014",
            "#ECEFF1"
          ],
          [
            "\u2014",
            "#ECEFF1"
          ]
        ]
      },
      "charge": [
        {
          "early": [
            "[ 650.  750.  850.  950. 1050. 1150. 1250. 1350. 1450. 1550. 1650. 1750.\n 1850. 1950. 2050. 2150. 2250. 2350. 2450.]",
            "[28.20000076 28.20000076 28.20000076 28.20000076 28.20000076 28.20000076\n 28.20000076 28.20000076 28.20000076 28.20000076 28.20000076 28.20000076\n 28.20000076 28.20000076 28.20000076 28.20000076 28.20000076 28.20000076\n 28.20000076]"
          ],
          "late": [
            "[ 650.  750.  850.  950. 1050. 1150. 1250. 1350. 1450. 1550. 1650. 1750.\n 1850. 1950. 2050. 2150. 2250. 2350.]",
            "[28.20000076 28.20000076 28.20000076 28.20000076 28.20000076 28.20000076\n 28.20000076 28.20000076 28.20000076 28.20000076 28.20000076 28.20000076\n 28.20000076 28.20000076 28.20000076 28.20000076 28.20000076 28.20000076]"
          ]
        }
      ],
      "risk": "green",
      "dname": "VIN23_NF_ALT"
    }
  },
  {
    "vin": "VIN14_NF_ALT",
    "dname": "VIN24_NF_ALT",
    "failed": false,
    "risk_band": "green",
    "est_km": 130089.77,
    "median_rul": 137.7,
    "fw_p25": 577.5,
    "fw_p75": 652.5,
    "fleet_med": 601.0,
    "rul_last": 137.87867486427825,
    "clock_zone_last": "YELLOW",
    "gap": null,
    "over_pred": null,
    "m5_trans": [],
    "m5_final": "GREEN",
    "m5_peak": null,
    "breaches": [],
    "ged": false,
    "ged_lead": null,
    "cdelta": 0.0,
    "n_cross": 1,
    "cross": [
      [
        "GREEN\u2192YELLOW",
        false,
        null
      ]
    ],
    "arch": "In-service \u2014 quiet",
    "snap": {
      "cols": [
        [
          "Early",
          "2024-07-02 00:00:00"
        ],
        [
          "Now",
          "2026-02-18 00:00:00"
        ]
      ],
      "col_index": {
        "Early": 0,
        "Now": 1
      },
      "rows": {
        "Effective zone": [
          [
            "GREEN",
            "#27AE60"
          ],
          [
            "YELLOW",
            "#F5A623"
          ]
        ],
        "RUL (schedule)": [
          [
            "657 d (GREEN)",
            "#27AE60"
          ],
          [
            "138 d (YELLOW)",
            "#F5A623"
          ]
        ],
        "Condition (M5)": [
          [
            "0.07 (GREEN)",
            "#27AE60"
          ],
          [
            "0.09 (GREEN)",
            "#27AE60"
          ]
        ],
        "VSI mean": [
          [
            "28.2 V",
            "#27AE60"
          ],
          [
            "28.1 V",
            "#27AE60"
          ]
        ],
        "Resting V": [
          [
            "nan V",
            "#27AE60"
          ],
          [
            "25.8 V",
            "#C0392B"
          ]
        ],
        "Sag rate": [
          [
            "0.00",
            "#27AE60"
          ],
          [
            "0.00",
            "#F5A623"
          ]
        ],
        "Crank-recovery": [
          [
            "-0.2\u03c3",
            "#27AE60"
          ],
          [
            "+0.1\u03c3",
            "#27AE60"
          ]
        ],
        "Reg. ceiling": [
          [
            "-0.2\u03c3",
            "#27AE60"
          ],
          [
            "-0.1\u03c3",
            "#27AE60"
          ]
        ],
        "GED2": [
          [
            "\u2014",
            "#ECEFF1"
          ],
          [
            "\u2014",
            "#ECEFF1"
          ]
        ]
      },
      "charge": [
        {
          "early": [
            "[ 650.  750.  850.  950. 1050. 1150. 1250. 1350. 1450. 1550. 1650. 1750.\n 1850. 1950. 2050. 2150. 2250. 2350. 2450.]",
            "[28.20000076 28.         28.         28.20000076 28.         28.\n 28.         28.         28.         28.         28.20000076 28.20000076\n 28.20000076 28.20000076 28.20000076 28.20000076 28.20000076 28.20000076\n 28.20000076]"
          ],
          "late": [
            "[ 650.  750.  850.  950. 1050. 1150. 1250. 1350. 1450. 1550. 1650. 1750.\n 1850. 1950. 2050. 2150. 2250. 2350. 2450.]",
            "[28.20000076 28.20000076 28.         28.20000076 28.20000076 28.20000076\n 28.20000076 28.20000076 28.20000076 28.20000076 28.20000076 28.20000076\n 28.20000076 28.20000076 28.20000076 28.20000076 28.20000076 28.20000076\n 28.20000076]"
          ]
        }
      ],
      "risk": "green",
      "dname": "VIN24_NF_ALT"
    }
  },
  {
    "vin": "VIN15_NF_ALT",
    "dname": "VIN25_NF_ALT",
    "failed": false,
    "risk_band": "amber",
    "est_km": 149991.94,
    "median_rul": 151.0,
    "fw_p25": 577.5,
    "fw_p75": 652.5,
    "fleet_med": 601.0,
    "rul_last": 151.25033687385462,
    "clock_zone_last": "YELLOW",
    "gap": null,
    "over_pred": null,
    "m5_trans": [
      [
        "May 2024",
        "YELLOW",
        "VSI volatility"
      ]
    ],
    "m5_final": "YELLOW",
    "m5_peak": "ORANGE",
    "breaches": [],
    "ged": false,
    "ged_lead": null,
    "cdelta": -0.20000076293945312,
    "n_cross": 1,
    "cross": [
      [
        "GREEN\u2192YELLOW",
        false,
        null
      ]
    ],
    "arch": "In-service \u2014 quiet",
    "snap": {
      "cols": [
        [
          "Early",
          "2024-03-01 00:00:00"
        ],
        [
          "Cond\u2192ORANGE",
          "2024-09-07 00:00:00"
        ],
        [
          "Now",
          "2025-09-26 00:00:00"
        ]
      ],
      "col_index": {
        "Early": 0,
        "Cond\u2192ORANGE": 1,
        "Now": 2
      },
      "rows": {
        "Effective zone": [
          [
            "GREEN",
            "#27AE60"
          ],
          [
            "YELLOW",
            "#F5A623"
          ],
          [
            "YELLOW",
            "#F5A623"
          ]
        ],
        "RUL (schedule)": [
          [
            "663 d (GREEN)",
            "#27AE60"
          ],
          [
            "475 d (GREEN)",
            "#27AE60"
          ],
          [
            "151 d (YELLOW)",
            "#F5A623"
          ]
        ],
        "Condition (M5)": [
          [
            "0.13 (GREEN)",
            "#27AE60"
          ],
          [
            "0.36 (ORANGE)",
            "#E67E22"
          ],
          [
            "0.18 (YELLOW)",
            "#F5A623"
          ]
        ],
        "VSI mean": [
          [
            "28.1 V",
            "#27AE60"
          ],
          [
            "28.1 V",
            "#27AE60"
          ],
          [
            "28.0 V",
            "#27AE60"
          ]
        ],
        "Resting V": [
          [
            "25.7 V",
            "#C0392B"
          ],
          [
            "24.9 V",
            "#C0392B"
          ],
          [
            "25.5 V",
            "#C0392B"
          ]
        ],
        "Sag rate": [
          [
            "0.00",
            "#F5A623"
          ],
          [
            "0.00",
            "#27AE60"
          ],
          [
            "0.00",
            "#27AE60"
          ]
        ],
        "Crank-recovery": [
          [
            "-0.1\u03c3",
            "#27AE60"
          ],
          [
            "+1.5\u03c3",
            "#F5A623"
          ],
          [
            "-0.0\u03c3",
            "#27AE60"
          ]
        ],
        "Reg. ceiling": [
          [
            "-0.3\u03c3",
            "#27AE60"
          ],
          [
            "+1.2\u03c3",
            "#F5A623"
          ],
          [
            "+0.2\u03c3",
            "#27AE60"
          ]
        ],
        "GED2": [
          [
            "\u2014",
            "#ECEFF1"
          ],
          [
            "\u2014",
            "#ECEFF1"
          ],
          [
            "\u2014",
            "#ECEFF1"
          ]
        ]
      },
      "charge": [
        {
          "early": [
            "[ 650.  750.  850.  950. 1050. 1150. 1250. 1350. 1450. 1550. 1650. 1750.\n 1850. 1950. 2050. 2150. 2250. 2350. 2450.]",
            "[28.         28.         28.         28.         28.         28.\n 28.         28.         28.20000076 28.         28.         28.\n 28.20000076 28.20000076 28.         28.         28.20000076 28.20000076\n 28.        ]"
          ],
          "late": [
            "[ 650.  750.  850.  950. 1050. 1150. 1250. 1350. 1450. 1550. 1650. 1750.\n 1850. 1950. 2050. 2150. 2250. 2350. 2450.]",
            "[27.79999924 27.79999924 27.79999924 27.79999924 27.79999924 27.79999924\n 27.79999924 27.79999924 27.79999924 27.79999924 27.79999924 27.79999924\n 27.79999924 27.79999924 28.         28.         28.         27.79999924\n 28.        ]"
          ]
        }
      ],
      "risk": "amber",
      "dname": "VIN25_NF_ALT"
    }
  }
]